my_package/__init__.py
veron_package_2312-0.1.0.dist-info/LICENSE.txt
veron_package_2312-0.1.0.dist-info/METADATA
veron_package_2312-0.1.0.dist-info/WHEEL
veron_package_2312-0.1.0.dist-info/top_level.txt
veron_package_2312-0.1.0.dist-info/RECORD
