Metadata-Version: 2.1
Name: veron-package-2312
Version: 0.1.0
Summary: A basic hello package
Home-page: https://gitbud.epam.com/veronika_krasilia
Author: Veronika Krasilia
Author-email: veronika_krasilia@epam.com
License: MIT
Platform: UNKNOWN
Classifier: Programming Language :: Python :: 3
Classifier: License :: OSI Approved :: MIT License
Classifier: Operating System :: OS Independent
Requires-Python: >=3.6
License-File: LICENSE.txt
